fim/Plugin.py
fim/__init__.py
fim/url.py
fimodule-0.0.3.dist-info/METADATA
fimodule-0.0.3.dist-info/WHEEL
fimodule-0.0.3.dist-info/top_level.txt
fimodule-0.0.3.dist-info/RECORD
